{
  "input": {
    "zipCode3Digit": "189",
    "shippingDate": "8/11/2023"
  },
  "url": "https://postcalc.usps.com/DomesticZoneChart/GetZoneChart?zipCode3Digit=189&shippingDate=8%2F11%2F2023&_=1691680013306",
  "originMin": "18900",
  "originMax": "18999",
  "requestedDate": {
    "y": 2023,
    "m": 8,
    "d": 11
  },
  "effectiveDateRaw": "August 1, 2023",
  "zip3s": [
    {
      "ZipCodes": "005",
      "Zone": "2",
      "MailService": ""
    },
    {
      "ZipCodes": "006---009",
      "Zone": "7",
      "MailService": ""
    },
    {
      "ZipCodes": "010---034",
      "Zone": "3",
      "MailService": ""
    },
    {
      "ZipCodes": "035",
      "Zone": "4",
      "MailService": ""
    },
    {
      "ZipCodes": "036---037",
      "Zone": "3",
      "MailService": ""
    },
    {
      "ZipCodes": "038---049",
      "Zone": "4",
      "MailService": ""
    },
    {
      "ZipCodes": "050---053",
      "Zone": "3",
      "MailService": ""
    },
    {
      "ZipCodes": "054",
      "Zone": "4",
      "MailService": ""
    },
    {
      "ZipCodes": "055",
      "Zone": "3",
      "MailService": ""
    },
    {
      "ZipCodes": "056",
      "Zone": "4",
      "MailService": ""
    },
    {
      "ZipCodes": "057",
      "Zone": "3",
      "MailService": ""
    },
    {
      "ZipCodes": "058---059",
      "Zone": "4",
      "MailService": ""
    },
    {
      "ZipCodes": "060---064",
      "Zone": "3",
      "MailService": ""
    },
    {
      "ZipCodes": "065---069",
      "Zone": "2",
      "MailService": ""
    },
    {
      "ZipCodes": "070",
      "Zone": "1",
      "MailService": ""
    },
    {
      "ZipCodes": "071---077",
      "Zone": "2",
      "MailService": ""
    },
    {
      "ZipCodes": "078---079",
      "Zone": "1",
      "MailService": ""
    },
    {
      "ZipCodes": "080---081",
      "Zone": "1*",
      "MailService": ""
    },
    {
      "ZipCodes": "082---084",
      "Zone": "2*",
      "MailService": ""
    },
    {
      "ZipCodes": "085---086",
      "Zone": "1",
      "MailService": ""
    },
    {
      "ZipCodes": "087",
      "Zone": "2",
      "MailService": ""
    },
    {
      "ZipCodes": "088---089",
      "Zone": "1",
      "MailService": ""
    },
    {
      "ZipCodes": "090---099",
      "Zone": "2+",
      "MailService": ""
    },
    {
      "ZipCodes": "100---119",
      "Zone": "2",
      "MailService": ""
    },
    {
      "ZipCodes": "120---123",
      "Zone": "3",
      "MailService": ""
    },
    {
      "ZipCodes": "124---127",
      "Zone": "2",
      "MailService": ""
    },
    {
      "ZipCodes": "128---136",
      "Zone": "3",
      "MailService": ""
    },
    {
      "ZipCodes": "137---139",
      "Zone": "2",
      "MailService": ""
    },
    {
      "ZipCodes": "140---148",
      "Zone": "3",
      "MailService": ""
    },
    {
      "ZipCodes": "149",
      "Zone": "2",
      "MailService": ""
    },
    {
      "ZipCodes": "150---168",
      "Zone": "3",
      "MailService": ""
    },
    {
      "ZipCodes": "169",
      "Zone": "3*",
      "MailService": ""
    },
    {
      "ZipCodes": "170---179",
      "Zone": "2*",
      "MailService": ""
    },
    {
      "ZipCodes": "180---181",
      "Zone": "1*",
      "MailService": ""
    },
    {
      "ZipCodes": "182---188",
      "Zone": "2*",
      "MailService": ""
    },
    {
      "ZipCodes": "189---196",
      "Zone": "1*",
      "MailService": ""
    },
    {
      "ZipCodes": "197",
      "Zone": "2*",
      "MailService": ""
    },
    {
      "ZipCodes": "198",
      "Zone": "1*",
      "MailService": ""
    },
    {
      "ZipCodes": "199",
      "Zone": "2*",
      "MailService": ""
    },
    {
      "ZipCodes": "200",
      "Zone": "2",
      "MailService": ""
    },
    {
      "ZipCodes": "201",
      "Zone": "3",
      "MailService": ""
    },
    {
      "ZipCodes": "202---205",
      "Zone": "2",
      "MailService": ""
    },
    {
      "ZipCodes": "206",
      "Zone": "3",
      "MailService": ""
    },
    {
      "ZipCodes": "207---212",
      "Zone": "2",
      "MailService": ""
    },
    {
      "ZipCodes": "214",
      "Zone": "2",
      "MailService": ""
    },
    {
      "ZipCodes": "215",
      "Zone": "3",
      "MailService": ""
    },
    {
      "ZipCodes": "216---219",
      "Zone": "2",
      "MailService": ""
    },
    {
      "ZipCodes": "220---221",
      "Zone": "3",
      "MailService": ""
    },
    {
      "ZipCodes": "222",
      "Zone": "2",
      "MailService": ""
    },
    {
      "ZipCodes": "223---239",
      "Zone": "3",
      "MailService": ""
    },
    {
      "ZipCodes": "240---243",
      "Zone": "4",
      "MailService": ""
    },
    {
      "ZipCodes": "244",
      "Zone": "3",
      "MailService": ""
    },
    {
      "ZipCodes": "245---253",
      "Zone": "4",
      "MailService": ""
    },
    {
      "ZipCodes": "254",
      "Zone": "3*",
      "MailService": ""
    },
    {
      "ZipCodes": "255---259",
      "Zone": "4",
      "MailService": ""
    },
    {
      "ZipCodes": "260",
      "Zone": "3",
      "MailService": ""
    },
    {
      "ZipCodes": "261",
      "Zone": "4",
      "MailService": ""
    },
    {
      "ZipCodes": "262",
      "Zone": "3",
      "MailService": ""
    },
    {
      "ZipCodes": "263---264",
      "Zone": "4",
      "MailService": ""
    },
    {
      "ZipCodes": "265",
      "Zone": "3",
      "MailService": ""
    },
    {
      "ZipCodes": "266",
      "Zone": "4",
      "MailService": ""
    },
    {
      "ZipCodes": "267---268",
      "Zone": "3",
      "MailService": ""
    },
    {
      "ZipCodes": "270---288",
      "Zone": "4",
      "MailService": ""
    },
    {
      "ZipCodes": "289",
      "Zone": "5",
      "MailService": ""
    },
    {
      "ZipCodes": "290---298",
      "Zone": "4",
      "MailService": ""
    },
    {
      "ZipCodes": "299---329",
      "Zone": "5",
      "MailService": ""
    },
    {
      "ZipCodes": "330---334",
      "Zone": "6",
      "MailService": ""
    },
    {
      "ZipCodes": "335---338",
      "Zone": "5",
      "MailService": ""
    },
    {
      "ZipCodes": "339---341",
      "Zone": "6",
      "MailService": ""
    },
    {
      "ZipCodes": "342",
      "Zone": "5",
      "MailService": ""
    },
    {
      "ZipCodes": "344",
      "Zone": "5",
      "MailService": ""
    },
    {
      "ZipCodes": "346---347",
      "Zone": "5",
      "MailService": ""
    },
    {
      "ZipCodes": "349---352",
      "Zone": "5",
      "MailService": ""
    },
    {
      "ZipCodes": "354---375",
      "Zone": "5",
      "MailService": ""
    },
    {
      "ZipCodes": "376---379",
      "Zone": "4",
      "MailService": ""
    },
    {
      "ZipCodes": "380---390",
      "Zone": "5",
      "MailService": ""
    },
    {
      "ZipCodes": "391---392",
      "Zone": "6",
      "MailService": ""
    },
    {
      "ZipCodes": "393",
      "Zone": "5",
      "MailService": ""
    },
    {
      "ZipCodes": "394---396",
      "Zone": "6",
      "MailService": ""
    },
    {
      "ZipCodes": "397---399",
      "Zone": "5",
      "MailService": ""
    },
    {
      "ZipCodes": "400",
      "Zone": "4",
      "MailService": ""
    },
    {
      "ZipCodes": "401",
      "Zone": "5",
      "MailService": ""
    },
    {
      "ZipCodes": "402---418",
      "Zone": "4",
      "MailService": ""
    },
    {
      "ZipCodes": "420---424",
      "Zone": "5",
      "MailService": ""
    },
    {
      "ZipCodes": "425---426",
      "Zone": "4",
      "MailService": ""
    },
    {
      "ZipCodes": "427",
      "Zone": "5",
      "MailService": ""
    },
    {
      "ZipCodes": "430---444",
      "Zone": "4",
      "MailService": ""
    },
    {
      "ZipCodes": "445",
      "Zone": "3",
      "MailService": ""
    },
    {
      "ZipCodes": "446---462",
      "Zone": "4",
      "MailService": ""
    },
    {
      "ZipCodes": "463---464",
      "Zone": "5",
      "MailService": ""
    },
    {
      "ZipCodes": "465---473",
      "Zone": "4",
      "MailService": ""
    },
    {
      "ZipCodes": "474---479",
      "Zone": "5",
      "MailService": ""
    },
    {
      "ZipCodes": "480---493",
      "Zone": "4",
      "MailService": ""
    },
    {
      "ZipCodes": "494",
      "Zone": "5",
      "MailService": ""
    },
    {
      "ZipCodes": "495---497",
      "Zone": "4",
      "MailService": ""
    },
    {
      "ZipCodes": "498---499",
      "Zone": "5",
      "MailService": ""
    },
    {
      "ZipCodes": "500",
      "Zone": "6",
      "MailService": ""
    },
    {
      "ZipCodes": "501---504",
      "Zone": "5",
      "MailService": ""
    },
    {
      "ZipCodes": "505",
      "Zone": "6",
      "MailService": ""
    },
    {
      "ZipCodes": "506---507",
      "Zone": "5",
      "MailService": ""
    },
    {
      "ZipCodes": "508",
      "Zone": "6",
      "MailService": ""
    },
    {
      "ZipCodes": "509",
      "Zone": "5",
      "MailService": ""
    },
    {
      "ZipCodes": "510---516",
      "Zone": "6",
      "MailService": ""
    },
    {
      "ZipCodes": "520---528",
      "Zone": "5",
      "MailService": ""
    },
    {
      "ZipCodes": "530---532",
      "Zone": "5",
      "MailService": ""
    },
    {
      "ZipCodes": "534---535",
      "Zone": "5",
      "MailService": ""
    },
    {
      "ZipCodes": "537---551",
      "Zone": "5",
      "MailService": ""
    },
    {
      "ZipCodes": "553",
      "Zone": "6",
      "MailService": ""
    },
    {
      "ZipCodes": "554---560",
      "Zone": "5",
      "MailService": ""
    },
    {
      "ZipCodes": "561---567",
      "Zone": "6",
      "MailService": ""
    },
    {
      "ZipCodes": "570---576",
      "Zone": "6",
      "MailService": ""
    },
    {
      "ZipCodes": "577",
      "Zone": "7",
      "MailService": ""
    },
    {
      "ZipCodes": "580---585",
      "Zone": "6",
      "MailService": ""
    },
    {
      "ZipCodes": "586---588",
      "Zone": "7",
      "MailService": ""
    },
    {
      "ZipCodes": "590---593",
      "Zone": "7",
      "MailService": ""
    },
    {
      "ZipCodes": "594",
      "Zone": "8",
      "MailService": ""
    },
    {
      "ZipCodes": "595",
      "Zone": "7",
      "MailService": ""
    },
    {
      "ZipCodes": "596---599",
      "Zone": "8",
      "MailService": ""
    },
    {
      "ZipCodes": "600---620",
      "Zone": "5",
      "MailService": ""
    },
    {
      "ZipCodes": "622---631",
      "Zone": "5",
      "MailService": ""
    },
    {
      "ZipCodes": "633---639",
      "Zone": "5",
      "MailService": ""
    },
    {
      "ZipCodes": "640---641",
      "Zone": "6",
      "MailService": ""
    },
    {
      "ZipCodes": "644---645",
      "Zone": "6",
      "MailService": ""
    },
    {
      "ZipCodes": "646",
      "Zone": "5",
      "MailService": ""
    },
    {
      "ZipCodes": "647---649",
      "Zone": "6",
      "MailService": ""
    },
    {
      "ZipCodes": "650---655",
      "Zone": "5",
      "MailService": ""
    },
    {
      "ZipCodes": "656",
      "Zone": "6",
      "MailService": ""
    },
    {
      "ZipCodes": "657---658",
      "Zone": "5",
      "MailService": ""
    },
    {
      "ZipCodes": "660---662",
      "Zone": "6",
      "MailService": ""
    },
    {
      "ZipCodes": "664---678",
      "Zone": "6",
      "MailService": ""
    },
    {
      "ZipCodes": "679",
      "Zone": "7",
      "MailService": ""
    },
    {
      "ZipCodes": "680---681",
      "Zone": "6",
      "MailService": ""
    },
    {
      "ZipCodes": "683---692",
      "Zone": "6",
      "MailService": ""
    },
    {
      "ZipCodes": "693",
      "Zone": "7",
      "MailService": ""
    },
    {
      "ZipCodes": "700---701",
      "Zone": "6",
      "MailService": ""
    },
    {
      "ZipCodes": "703---708",
      "Zone": "6",
      "MailService": ""
    },
    {
      "ZipCodes": "710---714",
      "Zone": "6",
      "MailService": ""
    },
    {
      "ZipCodes": "716---722",
      "Zone": "6",
      "MailService": ""
    },
    {
      "ZipCodes": "723---725",
      "Zone": "5",
      "MailService": ""
    },
    {
      "ZipCodes": "726---731",
      "Zone": "6",
      "MailService": ""
    },
    {
      "ZipCodes": "733",
      "Zone": "7",
      "MailService": ""
    },
    {
      "ZipCodes": "734---738",
      "Zone": "6",
      "MailService": ""
    },
    {
      "ZipCodes": "739",
      "Zone": "7",
      "MailService": ""
    },
    {
      "ZipCodes": "740---741",
      "Zone": "6",
      "MailService": ""
    },
    {
      "ZipCodes": "743---763",
      "Zone": "6",
      "MailService": ""
    },
    {
      "ZipCodes": "764---765",
      "Zone": "7",
      "MailService": ""
    },
    {
      "ZipCodes": "766---767",
      "Zone": "6",
      "MailService": ""
    },
    {
      "ZipCodes": "768---769",
      "Zone": "7",
      "MailService": ""
    },
    {
      "ZipCodes": "770",
      "Zone": "6",
      "MailService": ""
    },
    {
      "ZipCodes": "772---778",
      "Zone": "6",
      "MailService": ""
    },
    {
      "ZipCodes": "779---798",
      "Zone": "7",
      "MailService": ""
    },
    {
      "ZipCodes": "799",
      "Zone": "8",
      "MailService": ""
    },
    {
      "ZipCodes": "800---816",
      "Zone": "7",
      "MailService": ""
    },
    {
      "ZipCodes": "820",
      "Zone": "7",
      "MailService": ""
    },
    {
      "ZipCodes": "821",
      "Zone": "8",
      "MailService": ""
    },
    {
      "ZipCodes": "822---829",
      "Zone": "7",
      "MailService": ""
    },
    {
      "ZipCodes": "830---838",
      "Zone": "8",
      "MailService": ""
    },
    {
      "ZipCodes": "840---847",
      "Zone": "8",
      "MailService": ""
    },
    {
      "ZipCodes": "850---853",
      "Zone": "8",
      "MailService": ""
    },
    {
      "ZipCodes": "855---857",
      "Zone": "8",
      "MailService": ""
    },
    {
      "ZipCodes": "859---860",
      "Zone": "8",
      "MailService": ""
    },
    {
      "ZipCodes": "863---865",
      "Zone": "8",
      "MailService": ""
    },
    {
      "ZipCodes": "870---871",
      "Zone": "7",
      "MailService": ""
    },
    {
      "ZipCodes": "873",
      "Zone": "8",
      "MailService": ""
    },
    {
      "ZipCodes": "874---875",
      "Zone": "7",
      "MailService": ""
    },
    {
      "ZipCodes": "876",
      "Zone": "8",
      "MailService": ""
    },
    {
      "ZipCodes": "877",
      "Zone": "7",
      "MailService": ""
    },
    {
      "ZipCodes": "878---880",
      "Zone": "8",
      "MailService": ""
    },
    {
      "ZipCodes": "881---884",
      "Zone": "7",
      "MailService": ""
    },
    {
      "ZipCodes": "885",
      "Zone": "8",
      "MailService": ""
    },
    {
      "ZipCodes": "889---891",
      "Zone": "8",
      "MailService": ""
    },
    {
      "ZipCodes": "893---895",
      "Zone": "8",
      "MailService": ""
    },
    {
      "ZipCodes": "897---898",
      "Zone": "8",
      "MailService": ""
    },
    {
      "ZipCodes": "900---908",
      "Zone": "8",
      "MailService": ""
    },
    {
      "ZipCodes": "910---928",
      "Zone": "8",
      "MailService": ""
    },
    {
      "ZipCodes": "930---961",
      "Zone": "8",
      "MailService": ""
    },
    {
      "ZipCodes": "962---966",
      "Zone": "8+",
      "MailService": ""
    },
    {
      "ZipCodes": "967---968",
      "Zone": "8",
      "MailService": ""
    },
    {
      "ZipCodes": "969",
      "Zone": "9+",
      "MailService": ""
    },
    {
      "ZipCodes": "970---986",
      "Zone": "8",
      "MailService": ""
    },
    {
      "ZipCodes": "988---999",
      "Zone": "8",
      "MailService": ""
    }
  ],
  "zip5s": [
    {
      "ZipCodes": "09000---09999",
      "Zone": "5",
      "MailService": "Priority Mail"
    },
    {
      "ZipCodes": "09000---09999",
      "Zone": "5",
      "MailService": "First-Class Mail"
    },
    {
      "ZipCodes": "96200---96699",
      "Zone": "5",
      "MailService": "Priority Mail"
    },
    {
      "ZipCodes": "96200---96699",
      "Zone": "5",
      "MailService": "First-Class Mail"
    },
    {
      "ZipCodes": "96900---96938",
      "Zone": "8",
      "MailService": ""
    },
    {
      "ZipCodes": "96945---96959",
      "Zone": "8",
      "MailService": ""
    },
    {
      "ZipCodes": "96961---96969",
      "Zone": "8",
      "MailService": ""
    },
    {
      "ZipCodes": "96971---96999",
      "Zone": "8",
      "MailService": ""
    }
  ]
}
